LSBSteg.py
__init__.py
steganography_package_joaoalves-0.0.1.dist-info/LICENSE
steganography_package_joaoalves-0.0.1.dist-info/METADATA
steganography_package_joaoalves-0.0.1.dist-info/WHEEL
steganography_package_joaoalves-0.0.1.dist-info/top_level.txt
steganography_package_joaoalves-0.0.1.dist-info/RECORD
